stackit/modelserving/__init__.py
stackit/modelserving/api/__init__.py
stackit/modelserving/api/default_api.py
stackit/modelserving/api_client.py
stackit/modelserving/api_response.py
stackit/modelserving/configuration.py
stackit/modelserving/exceptions.py
stackit/modelserving/models/__init__.py
stackit/modelserving/models/chat_model_details.py
stackit/modelserving/models/create_token_payload.py
stackit/modelserving/models/create_token_response.py
stackit/modelserving/models/embedding_model_details.py
stackit/modelserving/models/error_message_response.py
stackit/modelserving/models/get_chat_model_response.py
stackit/modelserving/models/get_embeddings_model_resp.py
stackit/modelserving/models/get_token_response.py
stackit/modelserving/models/list_models_response.py
stackit/modelserving/models/list_token_resp.py
stackit/modelserving/models/message_response.py
stackit/modelserving/models/model.py
stackit/modelserving/models/partial_update_token_payload.py
stackit/modelserving/models/sku.py
stackit/modelserving/models/token.py
stackit/modelserving/models/token_created.py
stackit/modelserving/models/update_token_response.py
stackit/modelserving/py.typed
stackit/modelserving/rest.py
stackit_modelserving-0.2.2.dist-info/METADATA
stackit_modelserving-0.2.2.dist-info/WHEEL
stackit_modelserving-0.2.2.dist-info/licenses/LICENSE.md
stackit_modelserving-0.2.2.dist-info/licenses/NOTICE.txt
stackit_modelserving-0.2.2.dist-info/RECORD
